aws_utils/__init__.py
aws_utils/awsutils.py
aws_utils_23408189-0.1.1.dist-info/licenses/LICENSE
aws_utils_23408189-0.1.1.dist-info/METADATA
aws_utils_23408189-0.1.1.dist-info/WHEEL
aws_utils_23408189-0.1.1.dist-info/top_level.txt
aws_utils_23408189-0.1.1.dist-info/RECORD
