Metadata-Version: 2.4
Name: aws-utils_23408189
Version: 0.1.1
Summary: aws utils for my projects 
Home-page: https://github.com/pypa/sampleproject
Author: shritiz kumar
Author-email: shritizk@gmail.com
Classifier: Programming Language :: Python :: 3
Classifier: License :: OSI Approved :: MIT License
Classifier: Operating System :: OS Independent
Requires-Python: >=3.6
License-File: LICENSE
Dynamic: author
Dynamic: author-email
Dynamic: classifier
Dynamic: description-content-type
Dynamic: home-page
Dynamic: license-file
Dynamic: requires-python
Dynamic: summary
